funkyml/classification.py
funkyml/funky.py
funky_ml-0.1.4.dist-info/METADATA
funky_ml-0.1.4.dist-info/WHEEL
funky_ml-0.1.4.dist-info/top_level.txt
funky_ml-0.1.4.dist-info/RECORD
