Metadata-Version: 2.1
Name: funky-ml
Version: 0.1.4
Summary: Automated ML by GD-Singh
Home-page: https://github.com/GD-Singh011/funky-ml
Author: Gagandeep Singh
Author-email: gdswasir@gmail.com
License: MIT
Keywords: funkyml,AutoML,Python
Platform: UNKNOWN
Classifier: Development Status :: 3 - Alpha
Classifier: Intended Audience :: Developers
Classifier: Topic :: Software Development :: Build Tools
Classifier: License :: OSI Approved :: MIT License
Classifier: Programming Language :: Python :: 3
Classifier: Programming Language :: Python :: 3.4
Classifier: Programming Language :: Python :: 3.5
Classifier: Programming Language :: Python :: 3.6
Requires-Dist: numpy
Requires-Dist: pandas
Requires-Dist: scipy
Requires-Dist: seaborn
Requires-Dist: matplotlib
Requires-Dist: scikit-learn
Requires-Dist: imblearn
Requires-Dist: xgboost
Requires-Dist: lightgbm
